gramag-0.4.1.dist-info/METADATA
gramag-0.4.1.dist-info/WHEEL
gramag-0.4.1.dist-info/licenses/LICENSE
gramag/__init__.py
gramag/gramag.cpython-311-i386-linux-gnu.so
gramag-0.4.1.dist-info/RECORD
