Metadata-Version: 2.3
Name: gramag
Version: 0.4.1
Classifier: Programming Language :: Rust
Classifier: Programming Language :: Python :: Implementation :: CPython
Classifier: Programming Language :: Python :: Implementation :: PyPy
License-File: LICENSE
Summary: Graph Magnitude Homology in Rust, with Python bindings
License: MIT
Requires-Python: >=3.7
Project-URL: Source Code, https://github.com/tomchaplin/gramag
